comfy/LICENSE.txt
comfy/checkpoint_pickle.py
comfy/cldm/cldm.py
comfy/cli_args.py
comfy/clip_config_bigg.json
comfy/clip_model.py
comfy/clip_vision.py
comfy/clip_vision_config_g.json
comfy/clip_vision_config_h.json
comfy/clip_vision_config_vitl.json
comfy/comfy_extras/chainner_models/__init__.py
comfy/comfy_extras/chainner_models/architecture/DAT.py
comfy/comfy_extras/chainner_models/architecture/HAT.py
comfy/comfy_extras/chainner_models/architecture/LICENSE-DAT
comfy/comfy_extras/chainner_models/architecture/LICENSE-ESRGAN
comfy/comfy_extras/chainner_models/architecture/LICENSE-HAT
comfy/comfy_extras/chainner_models/architecture/LICENSE-RealESRGAN
comfy/comfy_extras/chainner_models/architecture/LICENSE-SCUNet
comfy/comfy_extras/chainner_models/architecture/LICENSE-SPSR
comfy/comfy_extras/chainner_models/architecture/LICENSE-SwiftSRGAN
comfy/comfy_extras/chainner_models/architecture/LICENSE-Swin2SR
comfy/comfy_extras/chainner_models/architecture/LICENSE-SwinIR
comfy/comfy_extras/chainner_models/architecture/LICENSE-lama
comfy/comfy_extras/chainner_models/architecture/LaMa.py
comfy/comfy_extras/chainner_models/architecture/OmniSR/ChannelAttention.py
comfy/comfy_extras/chainner_models/architecture/OmniSR/LICENSE
comfy/comfy_extras/chainner_models/architecture/OmniSR/OSA.py
comfy/comfy_extras/chainner_models/architecture/OmniSR/OSAG.py
comfy/comfy_extras/chainner_models/architecture/OmniSR/OmniSR.py
comfy/comfy_extras/chainner_models/architecture/OmniSR/esa.py
comfy/comfy_extras/chainner_models/architecture/OmniSR/layernorm.py
comfy/comfy_extras/chainner_models/architecture/OmniSR/pixelshuffle.py
comfy/comfy_extras/chainner_models/architecture/RRDB.py
comfy/comfy_extras/chainner_models/architecture/SCUNet.py
comfy/comfy_extras/chainner_models/architecture/SPSR.py
comfy/comfy_extras/chainner_models/architecture/SRVGG.py
comfy/comfy_extras/chainner_models/architecture/SwiftSRGAN.py
comfy/comfy_extras/chainner_models/architecture/Swin2SR.py
nodetool-0.2.9.dist-info/LICENSE.txt
nodetool-0.2.9.dist-info/METADATA
nodetool-0.2.9.dist-info/WHEEL
nodetool-0.2.9.dist-info/entry_points.txt
nodetool-0.2.9.dist-info/RECORD
