Metadata-Version: 2.1
Name: nodetool
Version: 0.2.9
Summary: Nodetool is a no-code development environment for Artificial Intelligence, enabling the simple and intuitive creation of powerful AI workflows and their integration into existing applications.
Author: Matthias Georgi
Author-email: matti.georgi@gmail.com
Requires-Python: >=3.10,<4.0
Classifier: Programming Language :: Python :: 3
Classifier: Programming Language :: Python :: 3.10
Classifier: Programming Language :: Python :: 3.11
Classifier: Programming Language :: Python :: 3.12
Requires-Dist: aiofiles
Requires-Dist: anthropic
Requires-Dist: authlib
Requires-Dist: black
Requires-Dist: boto3 (>=1.34.5)
Requires-Dist: bs4
Requires-Dist: chromadb
Requires-Dist: click
Requires-Dist: cryptography
Requires-Dist: fastapi (>=0.109.0)
Requires-Dist: httpx
Requires-Dist: imageio
Requires-Dist: importlib-resources
Requires-Dist: itsdangerous
Requires-Dist: joblib
Requires-Dist: jsonpath-ng
Requires-Dist: librosa
Requires-Dist: matplotlib
Requires-Dist: moto[s3]
Requires-Dist: moviepy
Requires-Dist: numpy (<2)
Requires-Dist: ollama
Requires-Dist: openai (>=1.10.0)
Requires-Dist: openapi-pydantic
Requires-Dist: opencv-python-headless
Requires-Dist: pandas
Requires-Dist: pedalboard
Requires-Dist: pillow
Requires-Dist: pydantic (>=2.6.1)
Requires-Dist: pydub
Requires-Dist: pymemcache
Requires-Dist: pyngrok
Requires-Dist: python-multipart
Requires-Dist: replicate
Requires-Dist: respx
Requires-Dist: scikit-image
Requires-Dist: scikit-learn
Requires-Dist: scipy
Requires-Dist: seaborn
Requires-Dist: tiktoken
Requires-Dist: uvicorn[standard]
Requires-Dist: validate_email
Requires-Dist: websockets
Requires-Dist: zipp
